[{"area_id":14,"name":"大東公園フェンス","lat":43.0367786,"long":141.4018187,"status":0,"note":null},{"area_id":14,"name":"登米市民病院東側花壇","lat":38.6874841,"long":141.1927616,"status":0,"note":null},{"area_id":14,"name":"登米市迫図書館","lat":38.6894739,"long":141.1956892,"status":0,"note":null},{"area_id":14,"name":"東北労働金庫向い市道敷","lat":38.6905333,"long":141.1905238,"status":0,"note":null},{"area_id":14,"name":"登米市歴史博物館南側歩道","lat":38.6939425,"long":141.194866,"status":0,"note":null},{"area_id":14,"name":"登米市役所前","lat":38.691411,"long":141.1883473,"status":0,"note":null},{"area_id":14,"name":"萩洗ふれあい公園","lat":38.6879586,"long":141.18137,"status":0,"note":null},{"area_id":14,"name":"迫大網住宅北側","lat":38.6797095,"long":141.1931732,"status":0,"note":null},{"area_id":14,"name":"江合集会所前フェンス","lat":38.680772,"long":141.1866437,"status":0,"note":null},{"area_id":14,"name":"斉藤建業南側個人所有空地","lat":38.6847038,"long":141.2091987,"status":0,"note":null},{"area_id":14,"name":"光文堂倉庫脇","lat":38.6851105,"long":141.2035988,"status":0,"note":null},{"area_id":14,"name":"登米市立佐沼小学校西側入口","lat":38.687615,"long":141.2023319,"status":0,"note":null},{"area_id":14,"name":"みやぎ登米農協デイサービスセンター西側フェンス","lat":38.6899491,"long":141.204597,"status":0,"note":null},{"area_id":14,"name":"個人宅前三角道路敷","lat":38.6914608,"long":141.2013528,"status":0,"note":null},{"area_id":14,"name":"登米市迫武道館南側花壇","lat":38.6948531,"long":141.199609,"status":0,"note":null},{"area_id":14,"name":"迫梅ノ木公園多目的広場南側","lat":38.6967623,"long":141.2064922,"status":0,"note":null},{"area_id":14,"name":"首無バス停付近市道敷","lat":38.6584757,"long":141.2211951,"status":0,"note":null},{"area_id":14,"name":"登米市森公民館前","lat":38.6717704,"long":141.2157583,"status":0,"note":null},{"area_id":14,"name":"個人宅塀","lat":38.679399,"long":141.2148906,"status":0,"note":null},{"area_id":14,"name":"鈴木酒店北側ゲートボール場","lat":38.6837002,"long":141.2213406,"status":0,"note":null},{"area_id":14,"name":"宮城西濃運輸㈱跡地前国道敷","lat":38.7054602,"long":141.1831302,"status":0,"note":null},{"area_id":14,"name":"北方公民館西側駐車場フェンス","lat":38.7024686,"long":141.1609315,"status":0,"note":null},{"area_id":14,"name":"泥内生活センター向い市道敷","lat":38.6829289,"long":141.1567755,"status":0,"note":null},{"area_id":14,"name":"迫新下谷地住宅駐車場フェンス","lat":38.7147688,"long":141.1718745,"status":0,"note":null},{"area_id":14,"name":"新大瀬・新一番江線市道敷","lat":38.7277987,"long":141.1611837,"status":0,"note":null},{"area_id":14,"name":"飯土井公民館向い歩道フェンス","lat":38.7215736,"long":141.1508729,"status":0,"note":null},{"area_id":14,"name":"長沼フートピア公園駐車場","lat":38.6890874,"long":141.1343478,"status":0,"note":null},{"area_id":14,"name":"消防団第５分団ポンプ倉庫脇","lat":38.6953878,"long":141.164182,"status":0,"note":null},{"area_id":14,"name":"市道石打坂・西舘線福祉ゾーン入口フェンス","lat":38.6921736,"long":141.174419,"status":0,"note":null},{"area_id":14,"name":"新田バイパス丁字路","lat":38.7172837,"long":141.1351735,"status":0,"note":null},{"area_id":14,"name":"JAみやぎ登米新田支店前丁字路","lat":38.7095951,"long":141.1215192,"status":0,"note":null},{"area_id":14,"name":"倉崎集落センター前","lat":38.7136061,"long":141.1463958,"status":0,"note":null},{"area_id":14,"name":"市道新田駅前山ノ神線山ノ神神社前丁字路","lat":38.7090765,"long":141.1395988,"status":0,"note":null},{"area_id":14,"name":"個人宅前","lat":38.6980492,"long":141.1265887,"status":0,"note":null},{"area_id":14,"name":"登米市立新田中学校フェンス","lat":38.6996439,"long":141.1090861,"status":0,"note":null},{"area_id":14,"name":"品の浦生活センター前市道敷","lat":38.7103973,"long":141.1103088,"status":0,"note":null},{"area_id":14,"name":"消防団第10分団ポンプ倉庫脇","lat":38.7029701,"long":141.098387,"status":0,"note":null},{"area_id":14,"name":"消防団第９分団ポンプ倉庫","lat":38.6576553,"long":141.0866368,"status":0,"note":null},{"area_id":14,"name":"個人宅東側丁字路","lat":38.6889211,"long":141.0947459,"status":0,"note":null},{"area_id":14,"name":"㈱登米精巧東側市道敷","lat":38.6734819,"long":141.0900887,"status":0,"note":null},{"area_id":14,"name":"立戸集落センター向い県道敷","lat":38.6747661,"long":141.1154073,"status":0,"note":null},{"area_id":14,"name":"東北新生園職員更衣棟（現場）北側","lat":38.6816631,"long":141.0631589,"status":0,"note":null},{"area_id":14,"name":"教育資料館敷地内（秋山写真店向い）","lat":38.6559851,"long":141.27981,"status":0,"note":null},{"area_id":14,"name":"個人宅東側フェンス","lat":38.6537724,"long":141.2770596,"status":0,"note":null},{"area_id":14,"name":"個人宅脇市道敷","lat":38.6562854,"long":141.2735852,"status":0,"note":null},{"area_id":14,"name":"旧アトリエ・エダ敷地内","lat":38.6576247,"long":141.2840491,"status":0,"note":null},{"area_id":14,"name":"蛭沢遊園地付近","lat":38.6661008,"long":141.2775662,"status":0,"note":null},{"area_id":14,"name":"登米遠見台住宅掲示板脇市道敷","lat":38.66089,"long":141.2780748,"status":0,"note":null},{"area_id":14,"name":"旧割烹若鮨とよま館向い県道敷","lat":38.6690966,"long":141.2704547,"status":0,"note":null},{"area_id":14,"name":"個人宅前市道敷","lat":38.6569225,"long":141.2762537,"status":0,"note":null},{"area_id":14,"name":"個人宅前市道ガードパイプ","lat":38.6510943,"long":141.2674911,"status":0,"note":null},{"area_id":14,"name":"特別養護老人ホーム東側市道敷","lat":38.6470282,"long":141.2697286,"status":0,"note":null},{"area_id":14,"name":"個人宅塀","lat":38.6507269,"long":141.2736014,"status":0,"note":null},{"area_id":14,"name":"登米老人福祉センター前","lat":38.6508925,"long":141.2784733,"status":0,"note":null},{"area_id":14,"name":"個人宅付近堤敷","lat":38.6423064,"long":141.2816995,"status":0,"note":null},{"area_id":14,"name":"警察資料館東側塀","lat":38.6513406,"long":141.2814216,"status":0,"note":null},{"area_id":14,"name":"とよまつづら淵地区多目的センター","lat":38.6506102,"long":141.2527408,"status":0,"note":null},{"area_id":14,"name":"個人宅前道路敷","lat":38.6607628,"long":141.2491614,"status":0,"note":null},{"area_id":14,"name":"旧小島会館前ロータリー県道敷","lat":38.6503373,"long":141.2564704,"status":0,"note":null},{"area_id":14,"name":"個人宅前","lat":38.6406504,"long":141.2572876,"status":0,"note":null},{"area_id":14,"name":"子持杉神社社務所前","lat":38.6457232,"long":141.2542125,"status":0,"note":null},{"area_id":14,"name":"市道新中通線交差点脇雑種地","lat":38.6519135,"long":141.2903885,"status":0,"note":null},{"area_id":14,"name":"個人宅塀","lat":38.6485278,"long":141.2895459,"status":0,"note":null},{"area_id":14,"name":"個人宅前市道敷","lat":38.6346662,"long":141.2931627,"status":0,"note":null},{"area_id":14,"name":"斥候川管理橋前市道敷","lat":38.662251,"long":141.3046573,"status":0,"note":null},{"area_id":14,"name":"平杉橋向い歩道フェンス","lat":38.656194,"long":141.3113249,"status":0,"note":null},{"area_id":14,"name":"登米林業活動センター前県道敷","lat":38.6824345,"long":141.3578355,"status":0,"note":null},{"area_id":14,"name":"登米市東和城内住宅フェンス","lat":38.7118542,"long":141.291902,"status":0,"note":null},{"area_id":14,"name":"登米市米谷病院前堤防敷","lat":38.7055365,"long":141.2882388,"status":0,"note":null},{"area_id":14,"name":"登米市米谷公民館フェンス","lat":38.7085359,"long":141.2907282,"status":0,"note":null},{"area_id":14,"name":"東和楼台コミュニティセンター","lat":38.689268,"long":141.2984811,"status":0,"note":null},{"area_id":14,"name":"個人宅前市道敷","lat":38.6965336,"long":141.3095829,"status":0,"note":null},{"area_id":14,"name":"佐藤商店付近国道敷","lat":38.7149747,"long":141.3197814,"status":0,"note":null},{"area_id":14,"name":"東和相川平倉地区多目的集会施設","lat":38.7157145,"long":141.3291049,"status":0,"note":null},{"area_id":14,"name":"東和根廻地区多目的集会施設","lat":38.7236177,"long":141.3034112,"status":0,"note":null},{"area_id":14,"name":"東和細野集会所フェンス","lat":38.7355418,"long":141.3062203,"status":0,"note":null},{"area_id":14,"name":"東和大沢農村公園フェンス市道敷","lat":38.7394099,"long":141.2982414,"status":0,"note":null},{"area_id":14,"name":"東和総合支所敷地北側","lat":38.7426807,"long":141.3160709,"status":0,"note":null},{"area_id":14,"name":"東和鱒渕生活改善センターフェンス","lat":38.7492158,"long":141.3332634,"status":0,"note":null},{"area_id":14,"name":"旧米川公民館跡地","lat":38.7726183,"long":141.3287701,"status":0,"note":null},{"area_id":14,"name":"消防団米川地区本部敷地フェンス","lat":38.7650171,"long":141.3271116,"status":0,"note":null},{"area_id":14,"name":"米川公民館フェンス前市道敷","lat":38.771453,"long":141.3606639,"status":0,"note":null},{"area_id":14,"name":"東和綱木公園前","lat":34.503115,"long":133.3875144,"status":0,"note":null},{"area_id":14,"name":"西上沢バス停前国道敷","lat":38.771453,"long":141.3606639,"status":0,"note":null},{"area_id":14,"name":"旧登米市東和国際交流センター","lat":38.7832524,"long":141.3685231,"status":0,"note":null},{"area_id":14,"name":"個人宅塀","lat":38.7821271,"long":141.3818203,"status":0,"note":null},{"area_id":14,"name":"鱒渕簡易郵便局前県道敷","lat":38.7531117,"long":141.3403815,"status":0,"note":null},{"area_id":14,"name":"東和馬の足農村公園内","lat":38.7565219,"long":141.3647427,"status":0,"note":null},{"area_id":14,"name":"消防団錦織地区本部敷地","lat":38.7278323,"long":141.2756918,"status":0,"note":null},{"area_id":14,"name":"登米市消防署東出張所敷地","lat":38.731233,"long":141.2809879,"status":0,"note":null},{"area_id":14,"name":"個人宅前掲示場脇市道敷","lat":38.7222034,"long":141.2805612,"status":0,"note":null},{"area_id":14,"name":"東和機織沼多目的共同利用施設","lat":38.7569805,"long":141.2880565,"status":0,"note":null},{"area_id":14,"name":"個人宅道路向（防火水槽脇）","lat":38.7587538,"long":141.2851212,"status":0,"note":null},{"area_id":14,"name":"旧旭屋前市道敷","lat":38.7569805,"long":141.2880565,"status":0,"note":null},{"area_id":14,"name":"個人宅地","lat":38.7209618,"long":141.2118869,"status":0,"note":null},{"area_id":14,"name":"個人宅前(白地集会所向かい)","lat":38.7356095,"long":141.210987,"status":0,"note":null},{"area_id":14,"name":"二ツ木遊園地フェンス","lat":38.7268672,"long":141.2197267,"status":0,"note":null},{"area_id":14,"name":"石森・金谷線市道敷","lat":38.7254195,"long":141.2281727,"status":0,"note":null},{"area_id":14,"name":"個人宅向い県道敷","lat":38.7342985,"long":141.2168465,"status":0,"note":null},{"area_id":14,"name":"阿部建設前道路敷地空地区画","lat":38.7405493,"long":141.2179677,"status":0,"note":null},{"area_id":14,"name":"細谷ふれあいセンター前","lat":38.7099769,"long":141.2020821,"status":0,"note":null},{"area_id":14,"name":"個人所有農地","lat":38.7099769,"long":141.2020821,"status":0,"note":null},{"area_id":14,"name":"個人宅南側道路沿い、個人所有畑","lat":38.7150408,"long":141.2090879,"status":0,"note":null},{"area_id":14,"name":"個人宅塀","lat":38.7008044,"long":141.2260571,"status":0,"note":null},{"area_id":14,"name":"個人宅塀","lat":38.7078629,"long":141.2200552,"status":0,"note":null},{"area_id":14,"name":"愛菜館入り口","lat":38.699339,"long":141.2179705,"status":0,"note":null},{"area_id":14,"name":"個人宅塀","lat":38.7087584,"long":141.2161514,"status":0,"note":null},{"area_id":14,"name":"中田かがの公園西側","lat":38.7029546,"long":141.2145908,"status":0,"note":null},{"area_id":14,"name":"個人宅塀","lat":38.6975237,"long":141.2142281,"status":0,"note":null},{"area_id":14,"name":"中田なかよし公園東側フェンス","lat":43.0498785,"long":141.3290768,"status":0,"note":null},{"area_id":14,"name":"みやぎ登米農協なかだ支店倉庫南側","lat":38.7135439,"long":141.2201096,"status":0,"note":null},{"area_id":14,"name":"登米市立中田中学校北側フェンス(蓬原会館向かい)","lat":38.7051498,"long":141.2370964,"status":0,"note":null},{"area_id":14,"name":"個人宅塀","lat":38.7086411,"long":141.2459183,"status":0,"note":null},{"area_id":14,"name":"個人所有空地","lat":38.7192894,"long":141.2451924,"status":0,"note":null},{"area_id":14,"name":"個人宅塀","lat":38.7110651,"long":141.2354933,"status":0,"note":null},{"area_id":14,"name":"中田大柳住宅前(１号室道路側)","lat":38.7140363,"long":141.2321127,"status":0,"note":null},{"area_id":14,"name":"個人所有作業場脇","lat":38.7187156,"long":141.2519281,"status":0,"note":null},{"area_id":14,"name":"個人宅塀","lat":38.7007706,"long":141.2479782,"status":0,"note":null},{"area_id":14,"name":"個人宅塀","lat":38.6941812,"long":141.2428665,"status":0,"note":null},{"area_id":14,"name":"登米市宝江ふれあいセンター","lat":38.6975163,"long":141.2435497,"status":0,"note":null},{"area_id":14,"name":"個人宅フェンス","lat":38.6758154,"long":141.2462772,"status":0,"note":null},{"area_id":14,"name":"個人宅塀","lat":38.6948736,"long":141.2378929,"status":0,"note":null},{"area_id":14,"name":"森六ふれあいセンター脇市道敷","lat":38.679785,"long":141.234272,"status":0,"note":null},{"area_id":14,"name":"個人宅前道路敷空地区画","lat":38.6806255,"long":141.2479455,"status":0,"note":null},{"area_id":14,"name":"個人宅塀","lat":38.6758154,"long":141.2462772,"status":0,"note":null},{"area_id":14,"name":"個人所有地（美容室駐車場）内","lat":38.6762563,"long":141.2510693,"status":0,"note":null},{"area_id":14,"name":"個人宅前","lat":38.6741119,"long":141.2502914,"status":0,"note":null},{"area_id":14,"name":"ＪＡみやぎ登米水稲種子温湯消毒センターフェンス","lat":38.7324103,"long":141.2618398,"status":0,"note":null},{"area_id":14,"name":"登米市立上沼小学校フェンス","lat":38.7309284,"long":141.2583047,"status":0,"note":null},{"area_id":14,"name":"弥勒寺北区集会所フェンス","lat":38.7365686,"long":141.2643855,"status":0,"note":null},{"area_id":14,"name":"金谷集会所フェンス","lat":38.7386817,"long":141.2501936,"status":0,"note":null},{"area_id":14,"name":"寺山集会所向い市道敷","lat":38.7342392,"long":141.2558539,"status":0,"note":null},{"area_id":14,"name":"個人宅塀","lat":38.7440123,"long":141.2576544,"status":0,"note":null},{"area_id":14,"name":"神ノ木転作研修センター南側畑","lat":38.7259612,"long":141.2546745,"status":0,"note":null},{"area_id":14,"name":"個人宅塀","lat":38.7236521,"long":141.2536054,"status":0,"note":null},{"area_id":14,"name":"長崎集落センター","lat":38.752293,"long":141.2551146,"status":0,"note":null},{"area_id":14,"name":"冠木ゲートボール場前","lat":38.7418371,"long":141.2672623,"status":0,"note":null},{"area_id":14,"name":"個人宅西側市道敷","lat":38.7486689,"long":141.2663808,"status":0,"note":null},{"area_id":14,"name":"個人宅前","lat":38.7560827,"long":141.2665222,"status":0,"note":null},{"area_id":14,"name":"個人宅塀","lat":38.7629677,"long":141.2689669,"status":0,"note":null},{"area_id":14,"name":"川面構造改善センター","lat":38.7201017,"long":141.2585578,"status":0,"note":null},{"area_id":14,"name":"個人宅塀","lat":38.7219042,"long":141.2582813,"status":0,"note":null},{"area_id":14,"name":"個人宅塀","lat":38.7077802,"long":141.265076,"status":0,"note":null},{"area_id":14,"name":"中田浅水農村公園市道敷","lat":38.7059638,"long":141.2669754,"status":0,"note":null},{"area_id":14,"name":"小島構造改善センター前","lat":38.6903782,"long":141.266816,"status":0,"note":null},{"area_id":14,"name":"個人宅塀","lat":38.6761856,"long":141.2716572,"status":0,"note":null},{"area_id":14,"name":"個人宅北側畑","lat":38.6939523,"long":141.2689766,"status":0,"note":null},{"area_id":14,"name":"沼畑公民館前駐車場フェンス","lat":38.6997446,"long":141.2735585,"status":0,"note":null},{"area_id":14,"name":"中田長谷山公園前市道敷","lat":38.6993467,"long":141.2798072,"status":0,"note":null},{"area_id":14,"name":"韓国家庭料理　サラン北側道路敷","lat":38.7048431,"long":141.2847357,"status":0,"note":null},{"area_id":14,"name":"豊里山根農村公園","lat":38.6164634,"long":141.2796123,"status":0,"note":null},{"area_id":14,"name":"個人宅向い（白鳥４号線法面）","lat":38.6063099,"long":141.2840791,"status":0,"note":null},{"area_id":14,"name":"個人宅脇（山根・白鳥線残地）","lat":38.6155671,"long":141.2917309,"status":0,"note":null},{"area_id":14,"name":"登米市立豊里小中学校南側フェンス","lat":38.5828025,"long":141.2512409,"status":0,"note":null},{"area_id":14,"name":"登米市立豊里小中学校北側フェンス","lat":38.5828025,"long":141.2512409,"status":0,"note":null},{"area_id":14,"name":"個人宅前市道敷（南幹道線）","lat":38.5847966,"long":141.2479827,"status":0,"note":null},{"area_id":14,"name":"定住促進住宅駐車場フェンス","lat":38.5907492,"long":141.2500665,"status":0,"note":null},{"area_id":14,"name":"個人所有畑","lat":38.6019418,"long":141.2605484,"status":0,"note":null},{"area_id":14,"name":"個人宅先市道敷（加々巻線）","lat":38.5916012,"long":141.2629806,"status":0,"note":null},{"area_id":14,"name":"登米みなみ商工会豊里支所駐車場","lat":38.5822273,"long":141.2445926,"status":0,"note":null},{"area_id":14,"name":"仲の松公園","lat":38.5799603,"long":141.2461217,"status":0,"note":null},{"area_id":14,"name":"市道川前四号線地内","lat":38.5733784,"long":141.2367324,"status":0,"note":null},{"area_id":14,"name":"豊里下屋浦公園","lat":38.5789894,"long":141.2388752,"status":0,"note":null},{"area_id":14,"name":"個人宅西側空地","lat":38.5783078,"long":141.2401148,"status":0,"note":null},{"area_id":14,"name":"個人宅道路向かい個人所有空地","lat":38.5984068,"long":141.2064135,"status":0,"note":null},{"area_id":14,"name":"大曲地区集落センター","lat":38.6005968,"long":141.227211,"status":0,"note":null},{"area_id":14,"name":"個人宅向い県道敷","lat":38.6012115,"long":141.2291844,"status":0,"note":null},{"area_id":14,"name":"個人宅先市道敷（竹花縦断線）","lat":38.5977981,"long":141.2402034,"status":0,"note":null},{"area_id":14,"name":"個人宅前市道敷（竹花縦断線）","lat":38.6059926,"long":141.238451,"status":0,"note":null},{"area_id":14,"name":"我妻工務店植栽センター脇道路敷","lat":38.6007159,"long":141.2425004,"status":0,"note":null},{"area_id":14,"name":"保手地区集落センター先","lat":38.6004781,"long":141.2526625,"status":0,"note":null},{"area_id":14,"name":"市道金山線・県道小島豊里線交差点南側","lat":38.6138615,"long":141.2496434,"status":0,"note":null},{"area_id":14,"name":"個人宅脇","lat":38.5743149,"long":141.2267923,"status":0,"note":null},{"area_id":14,"name":"二ツ屋生活センター","lat":38.5706066,"long":141.2198394,"status":0,"note":null},{"area_id":14,"name":"上谷地集会所","lat":38.5787938,"long":141.2015004,"status":0,"note":null},{"area_id":14,"name":"個人宅塀","lat":38.6321069,"long":141.2448296,"status":0,"note":null},{"area_id":14,"name":"森腰農地水看板設置場","lat":38.6401023,"long":141.2358599,"status":0,"note":null},{"area_id":14,"name":"個人宅雑種地","lat":38.6419596,"long":141.2358098,"status":0,"note":null},{"area_id":14,"name":"個人宅畑","lat":38.6398294,"long":141.2141574,"status":0,"note":null},{"area_id":14,"name":"鈴根バス停付近県道敷(菅原直行氏所有田法面)","lat":38.6211964,"long":141.2163991,"status":0,"note":null},{"area_id":14,"name":"登米市吉田体育館脇","lat":38.6278865,"long":141.2140864,"status":0,"note":null},{"area_id":14,"name":"登米リサイクル事業協同組合資源化共同施設フェンス","lat":38.6326131,"long":141.2127279,"status":0,"note":null},{"area_id":14,"name":"県道古川登米線(個人宅前防護フェンス)","lat":38.63138,"long":141.2225852,"status":0,"note":null},{"area_id":14,"name":"登米市吉田運動場(正面入り口側)","lat":38.6306532,"long":141.2179071,"status":0,"note":null},{"area_id":14,"name":"今泉生活センターフェンス","lat":38.6240319,"long":141.2224942,"status":0,"note":null},{"area_id":14,"name":"平筒沼ふれあい公園バス停付近駐車場","lat":38.6174483,"long":141.236092,"status":0,"note":null},{"area_id":14,"name":"山吉田集会所前","lat":38.6478255,"long":141.2146614,"status":0,"note":null},{"area_id":14,"name":"個人宅塀","lat":38.6544377,"long":141.2150734,"status":0,"note":null},{"area_id":14,"name":"登米羽黒児童遊園フェンス(狐崎集落センター脇)","lat":38.6098808,"long":141.2282291,"status":0,"note":null},{"area_id":14,"name":"個人宅塀","lat":38.6058905,"long":141.2271633,"status":0,"note":null},{"area_id":14,"name":"新田集落センター裏市道敷","lat":38.6038319,"long":141.2199596,"status":0,"note":null},{"area_id":14,"name":"中埣生活センター前水路敷","lat":38.6040638,"long":141.2134878,"status":0,"note":null},{"area_id":14,"name":"米山後小路農村公園","lat":38.6357576,"long":141.2007093,"status":0,"note":null},{"area_id":14,"name":"個人宅機械置場脇","lat":38.630722,"long":141.1992131,"status":0,"note":null},{"area_id":14,"name":"平埣生活センターフェンス","lat":38.6044268,"long":141.2005199,"status":0,"note":null},{"area_id":14,"name":"個人宅跡地塀","lat":38.626508,"long":141.2044027,"status":0,"note":null},{"area_id":14,"name":"個人宅塀","lat":38.6302027,"long":141.1957672,"status":0,"note":null},{"area_id":14,"name":"登米市米山体育館南側歩道境敷地","lat":38.6289633,"long":141.1893908,"status":0,"note":null},{"area_id":14,"name":"登米市立米山中学校体育館フェンス","lat":38.6318244,"long":141.1919918,"status":0,"note":null},{"area_id":14,"name":"砥落農事集会所","lat":38.6436748,"long":141.1738812,"status":0,"note":null},{"area_id":14,"name":"米山児童館フェンス","lat":38.6326465,"long":141.1962723,"status":0,"note":null},{"area_id":14,"name":"個人宅竹林前","lat":38.61782,"long":141.1737761,"status":0,"note":null},{"area_id":14,"name":"的場生活センターフェンス","lat":38.6197848,"long":141.1768466,"status":0,"note":null},{"area_id":14,"name":"個人宅裏（二瓶石油脇）","lat":38.6094683,"long":141.1758272,"status":0,"note":null},{"area_id":14,"name":"米山幼稚園前フェンス","lat":38.6216644,"long":141.1653158,"status":0,"note":null},{"area_id":14,"name":"個人宅塀","lat":38.6238538,"long":141.1553366,"status":0,"note":null},{"area_id":14,"name":"個人宅塀","lat":38.6264364,"long":141.153016,"status":0,"note":null},{"area_id":14,"name":"みやぎ登米農協短台店前駐車場","lat":38.6109438,"long":141.1636855,"status":0,"note":null},{"area_id":14,"name":"個人宅前市道敷","lat":38.6197611,"long":141.138781,"status":0,"note":null},{"area_id":14,"name":"千貫集会所塀","lat":38.6459624,"long":141.1348026,"status":0,"note":null},{"area_id":14,"name":"遠澤馬頭観世音前市道敷","lat":38.7612115,"long":141.1790985,"status":0,"note":null},{"area_id":14,"name":"第一区掲示板交差点花壇","lat":38.7566261,"long":141.191046,"status":0,"note":null},{"area_id":14,"name":"消防団石越支団第１分団消防ポンプ置場","lat":38.7581012,"long":141.1793102,"status":0,"note":null},{"area_id":14,"name":"寺山集会所前溜池前道路沿","lat":38.7714852,"long":141.1742459,"status":0,"note":null},{"area_id":14,"name":"第８区集会所前ガードレール先","lat":38.7698965,"long":141.1790612,"status":0,"note":null},{"area_id":14,"name":"個人宅後県道路敷","lat":38.767762,"long":141.1813264,"status":0,"note":null},{"area_id":14,"name":"大根の沢馬頭観世音脇県道路敷","lat":38.7489911,"long":141.1937466,"status":0,"note":null},{"area_id":14,"name":"佐々木理容所隣空地","lat":38.7655819,"long":141.1746315,"status":0,"note":null},{"area_id":14,"name":"個人宅向い前道路残地","lat":38.7584483,"long":141.2001182,"status":0,"note":null},{"area_id":14,"name":"個人宅向い道路敷","lat":38.7459915,"long":141.1580719,"status":0,"note":null},{"area_id":14,"name":"石越第３農村公園内市道敷","lat":38.7535119,"long":141.1642374,"status":0,"note":null},{"area_id":14,"name":"第四区生活センター内","lat":38.759313,"long":141.1624594,"status":0,"note":null},{"area_id":14,"name":"個人宅ブロック塀","lat":38.7674788,"long":141.1678613,"status":0,"note":null},{"area_id":14,"name":"石越陽だまり公園","lat":38.7680032,"long":141.1583247,"status":0,"note":null},{"area_id":14,"name":"個人所有畑","lat":38.7812536,"long":141.1592396,"status":0,"note":null},{"area_id":14,"name":"十八引防火水槽付近県道敷","lat":38.745129,"long":141.1957197,"status":0,"note":null},{"area_id":14,"name":"山根前4-2水路前フェンス","lat":38.7398631,"long":141.1997602,"status":0,"note":null},{"area_id":14,"name":"第14区コミュニティセンター","lat":38.7385876,"long":141.200461,"status":0,"note":null},{"area_id":14,"name":"おてんとさん向いゴミ集積所脇","lat":38.6711563,"long":141.182775,"status":0,"note":null},{"area_id":14,"name":"紅忠コイルセンター㈱前市道敷","lat":38.6709417,"long":141.1924549,"status":0,"note":null},{"area_id":14,"name":"大門公民館脇","lat":38.6663782,"long":141.1856548,"status":0,"note":null},{"area_id":14,"name":"細川公民館前脇","lat":38.6582372,"long":141.1824321,"status":0,"note":null},{"area_id":14,"name":"南方老人福祉センター西側市道敷","lat":38.6559281,"long":141.1881688,"status":0,"note":null},{"area_id":14,"name":"北大畑公民館向い市道敷","lat":38.6581763,"long":141.1997936,"status":0,"note":null},{"area_id":14,"name":"南大畑三叉路市道道路敷","lat":38.6485482,"long":141.2047146,"status":0,"note":null},{"area_id":14,"name":"大岳公民館向いゴミ集積所脇道路敷","lat":38.6552616,"long":141.171742,"status":0,"note":null},{"area_id":14,"name":"梶沼公民館前","lat":38.6426566,"long":141.1850305,"status":0,"note":null},{"area_id":14,"name":"板倉子ども会花壇脇","lat":38.6753859,"long":141.1670303,"status":0,"note":null},{"area_id":14,"name":"沢田公民館前","lat":38.6701714,"long":141.1619677,"status":0,"note":null},{"area_id":14,"name":"青島公民館前","lat":38.6667567,"long":141.1494807,"status":0,"note":null},{"area_id":14,"name":"月見橋西側駐車場","lat":38.6699328,"long":141.1461552,"status":0,"note":null},{"area_id":14,"name":"原公民館脇","lat":38.6643465,"long":141.17514,"status":0,"note":null},{"area_id":14,"name":"松葉公民館入口市道路肩","lat":38.6567645,"long":141.1744662,"status":0,"note":null},{"area_id":14,"name":"旧砥落公民館脇","lat":38.6477405,"long":141.1731969,"status":0,"note":null},{"area_id":14,"name":"大袋地内土手駐車場","lat":38.6454674,"long":141.1490112,"status":0,"note":null},{"area_id":14,"name":"山成公民館脇","lat":38.6599979,"long":141.1650708,"status":0,"note":null},{"area_id":14,"name":"新高石公民館前","lat":38.6593201,"long":141.1549423,"status":0,"note":null},{"area_id":14,"name":"高石公民館脇","lat":38.6595466,"long":141.1465859,"status":0,"note":null},{"area_id":14,"name":"苔下行政区ゴミ集積所隣県道敷","lat":38.6595604,"long":141.1377921,"status":0,"note":null},{"area_id":14,"name":"柳沢公民館向い南方柳沢農村公園","lat":38.9081672,"long":141.312674,"status":0,"note":null},{"area_id":14,"name":"個人宅裏ゴミ集積所脇","lat":38.6430422,"long":141.1009404,"status":0,"note":null},{"area_id":14,"name":"狼掛公民館前","lat":38.6559135,"long":141.1196919,"status":0,"note":null},{"area_id":14,"name":"畑岡公民館前","lat":38.6578602,"long":141.1156588,"status":0,"note":null},{"area_id":14,"name":"南方一ノ曲農村公園フェンス","lat":38.6465838,"long":141.1209438,"status":0,"note":null},{"area_id":14,"name":"苔上公民館向い歩道フェンス","lat":38.6612754,"long":141.1311207,"status":0,"note":null},{"area_id":14,"name":"平貝公民館脇","lat":38.6704173,"long":141.1201693,"status":0,"note":null},{"area_id":14,"name":"個人宅前","lat":38.5774573,"long":141.3025722,"status":0,"note":null},{"area_id":14,"name":"個人宅敷地","lat":38.6067872,"long":141.3007479,"status":0,"note":null},{"area_id":14,"name":"消防津山出張所駐車場フエンス","lat":38.609496,"long":141.3002646,"status":0,"note":null},{"area_id":14,"name":"本町３･４丁目多目的集会所フェンス","lat":38.6151311,"long":141.3001341,"status":0,"note":null},{"area_id":14,"name":"宮町公民館県道側フェンス","lat":38.6126919,"long":141.3028439,"status":0,"note":null},{"area_id":14,"name":"個人所有地（畑）","lat":38.6088168,"long":141.3170651,"status":0,"note":null},{"area_id":14,"name":"個人宅向市道敷","lat":38.6306938,"long":141.3051484,"status":0,"note":null},{"area_id":14,"name":"個人所有地","lat":38.6226864,"long":141.2964665,"status":0,"note":null},{"area_id":14,"name":"西下在農村公園内","lat":38.5777985,"long":141.2900303,"status":0,"note":null},{"area_id":14,"name":"長谷寺入口（現況公衆用道路敷）","lat":38.6253644,"long":141.3520855,"status":0,"note":null},{"area_id":14,"name":"個人宅塀","lat":38.6277326,"long":141.3482635,"status":0,"note":null},{"area_id":14,"name":"旧杉の子保育所フェンス","lat":38.6312341,"long":141.3512992,"status":0,"note":null},{"area_id":14,"name":"陸前横山駅前市道敷","lat":38.6314795,"long":141.354226,"status":0,"note":null},{"area_id":14,"name":"個人宅脇市道敷","lat":38.6290882,"long":141.3601569,"status":0,"note":null},{"area_id":14,"name":"個人宅塀","lat":38.6343843,"long":141.3597075,"status":0,"note":null},{"area_id":14,"name":"個人宅前","lat":38.6423523,"long":141.3645907,"status":0,"note":null},{"area_id":14,"name":"横山11区担い手センター手前右側（市道路肩）","lat":38.6300515,"long":141.3803831,"status":0,"note":null},{"area_id":14,"name":"個人宅前県道敷","lat":38.6041487,"long":141.3661287,"status":0,"note":null},{"area_id":14,"name":"旧南沢分校前ガードパイプ","lat":38.6091661,"long":141.3622901,"status":0,"note":null}]